<?xml version="1.0" encoding="utf-8" ?><dwsync><file name="LostPassword.html" server="idcmn.worldsecuresystems.com//" local="3408184800" remote="7703152096" Dst="-1" /><file name="Invoice.html" server="idcmn.worldsecuresystems.com//" local="3408184800" remote="7703152096" Dst="-1" /><file name="Order.html" server="idcmn.worldsecuresystems.com//" local="3408184800" remote="7703152096" Dst="-1" /><file name="Workflow3rdParty.html" server="idcmn.worldsecuresystems.com//" local="3408184800" remote="7703152096" Dst="-1" /><file name="ForumPostSubscriberAlert.html" server="idcmn.worldsecuresystems.com//" local="3408184800" remote="7703152096" Dst="-1" /><file name="ForumTopicSubscriberAlert.html" server="idcmn.worldsecuresystems.com//" local="3408184800" remote="7703152096" Dst="-1" /><file name="DoubleOptInEmail.html" server="idcmn.worldsecuresystems.com//" local="3408184800" remote="7703152096" Dst="-1" /><file name="SecureZoneDetails.html" server="idcmn.worldsecuresystems.com//" local="3408184800" remote="7703152096" Dst="-1" /><file name="AffiliateProgramDetails.html" server="idcmn.worldsecuresystems.com//" local="3408184800" remote="7703152096" Dst="-1" /><file name="GiftVoucherEmail.html" server="idcmn.worldsecuresystems.com//" local="3408184800" remote="7703152096" Dst="-1" /><file name="DropShipping.html" server="idcmn.worldsecuresystems.com//" local="3408184800" remote="7703152096" Dst="-1" /><file name="ReferAFriend.html" server="idcmn.worldsecuresystems.com//" local="3408184800" remote="7703152096" Dst="-1" /><file name="CSF.html" server="idcmn.worldsecuresystems.com//" local="3408184800" remote="7703152096" Dst="-1" /><file name="WorkflowNotification.html" server="idcmn.worldsecuresystems.com//" local="3477076634" remote="7772043931" Dst="-1" /><file name="WorkflowTask.html" server="idcmn.worldsecuresystems.com//" local="3477076635" remote="7772043933" Dst="-1" /><file name="WorkflowCompletion.html" server="idcmn.worldsecuresystems.com//" local="3477076633" remote="7772043930" Dst="-1" /><file name="WorkflowReminder.html" server="idcmn.worldsecuresystems.com//" local="3477076635" remote="7772043932" Dst="-1" /><file name="WorkflowEscalation.html" server="idcmn.worldsecuresystems.com//" local="3477076633" remote="7772043930" Dst="-1" /><file name="WorkflowRejection.html" server="idcmn.worldsecuresystems.com//" local="3477076634" remote="7772043931" Dst="-1" /></dwsync>